archive_rotator/__init__.py
archive_rotator/algorithms.py
archive_rotator/cli.py
archive_rotator/rotator.py
archive_rotator-0.2.1.dist-info/DESCRIPTION.rst
archive_rotator-0.2.1.dist-info/entry_points.txt
archive_rotator-0.2.1.dist-info/METADATA
archive_rotator-0.2.1.dist-info/metadata.json
archive_rotator-0.2.1.dist-info/RECORD
archive_rotator-0.2.1.dist-info/top_level.txt
archive_rotator-0.2.1.dist-info/WHEEL
