Metadata-Version: 2.0
Name: archive-rotator
Version: 0.2.1
Summary: Flexible utility for rotating backup files.
Home-page: https://github.com/maxharp3r/archive-rotator
Author: Max Harper
Author-email: maxharp3r@gmail.com
License: MIT License
Keywords: backup rotation
Platform: UNKNOWN
Classifier: Development Status :: 4 - Beta
Classifier: Intended Audience :: Developers
Classifier: Intended Audience :: System Administrators
Classifier: License :: OSI Approved :: MIT License
Classifier: Natural Language :: English
Classifier: Programming Language :: Python :: 2
Classifier: Programming Language :: Python :: 2.7
Classifier: Programming Language :: Python :: 3
Classifier: Programming Language :: Python :: 3.4
Classifier: Programming Language :: Python :: 3.5
Classifier: Topic :: System :: Archiving :: Backup
